kiwimouse/__about__.py
kiwimouse/__init__.py
kiwimouse-1.0.1.dist-info/METADATA
kiwimouse-1.0.1.dist-info/WHEEL
kiwimouse-1.0.1.dist-info/licenses/LICENSE
kiwimouse-1.0.1.dist-info/RECORD
