Metadata-Version: 2.3
Name: kiwimouse
Version: 1.0.1
Summary: Simulate mouse inputs in 3d DirectX games
Project-URL: Homepage, https://github.com/kezif/kiwimouse
Project-URL: Issues, https://github.com/kezif/kiwimouse/issues
Author-email: Kezif <kezif6262@gmail.com>
License-File: LICENSE
Classifier: Intended Audience :: Developers
Classifier: License :: OSI Approved :: GNU General Public License v3 (GPLv3)
Classifier: Operating System :: Microsoft :: Windows
Classifier: Programming Language :: Python :: 3
Classifier: Topic :: Games/Entertainment :: First Person Shooters
Classifier: Topic :: Software Development :: Testing
Requires-Python: >=3.9
